{"type": "Feature", "id": 12515454, "properties": {"woe:id": 12515454, "woe:parent_id": 538216, "woe:name": "Ponta Delgada Airport", "woe:placetype": 14, "woe:placetype_name": "Airport", "woe:lang": "ENG", "iso:country": "PT", "meta:provider": ["geoplanet:7.3.1", "geoplanet:7.3.2", "geoplanet:7.4.0", "geoplanet:7.4.1", "geoplanet:7.5.1", "geoplanet:7.5.2", "geoplanet:7.6.0", "geoplanet:7.8.1", "geoplanet:7.9.0", "geoplanet:7.10.0", "geoplanet:8.0.0", "woeplanet:8.0.0"], "meta:indexed": "2020-08-20T20:59:12.797995", "woe:alias_ENG_V": ["PDL Airport", "PDL"], "woe:alias_POR_V": ["Aeroport PDL", "PDL Aeroport"], "meta:updated": "2020-08-22T02:47:01.089455", "woe:hierarchy": {"continent": 24865675, "country": 23424925, "town": 0, "planet": 1, "county": 56071137, "suburb": 0, "state": 15021776, "region": 0, "localadmin": 0}, "woe:timezone_id": 28350868, "woe:hash": "eqtwxjzhf5xq", "woe:centroid": [-25.698299, 37.737499], "geom:latitude": 37.737499, "geom:longitude": -25.698299, "geom:hash": "eqtwxjzhf5xq", "woe:latitude": 37.737499, "geom:centroid": [-25.698299, 37.737499], "woe:longitude": -25.698299, "woe:repo": "woeplanet-airport-pt"}, "geometry": {"coordinates": [-25.698299, 37.737499], "type": "Point"}}